<?xml version="1.0" encoding="UTF-8"?>
<!-- /RobotsWorld.xml, jednostki w ukladzie SI -->
<World name="gate">
	<Robots>
		<Robot name="robot1" position_x="4.0" position_y="9.5" position_z="1" rotation_z="3.14" type="RobotCar"/>
		<Robot name="robot2" position_x="5.0" position_y="9.5" position_z="1" rotation_z="3.14" type="RobotCar"/>
		<!--<Robot name="robot3" position_x="6.0" position_y="9.5" position_z="1" rotation_z="3.14" type="RobotCar"/>-->
		<Robot name="robot4" position_x="4.0" position_y="0.5" position_z="1" rotation_z="0.0" type="RobotCar"/>
		<Robot name="robot5" position_x="5.0" position_y="0.5" position_z="1" rotation_z="0.0" type="RobotCar"/>
		<!--<Robot name="robot6" position_x="6.0" position_y="0.5" position_z="1" rotation_z="0.0" type="RobotCar"/>-->
	</Robots>
	<Environment>
		<Geoms>
			<!-- ground -->
			<Geom bouncyness="0.6" friction="1" position_x="5" position_y="5" position_z="0" rotation_x="0" rotation_y="0" rotation_z="0" size_x="10" size_y="10" size_z="0.1" type="box"/>
			<!-- world walls -->
			<Geom bouncyness="0.3" color="80003366" friction="0.0" position_x="5" position_y="10" position_z="1" rotation_x="0" rotation_y="0" rotation_z="0" size_x="10" size_y="0.1" size_z="2" type="box"/>
			<Geom bouncyness="0.3" color="80003366" friction="0.0" position_x="5" position_y="0" position_z="1" rotation_x="0" rotation_y="0" rotation_z="0" size_x="10" size_y="0.1" size_z="2" type="box"/>
			<Geom bouncyness="0.3" color="80003366" friction="0.0" position_x="10" position_y="5" position_z="1" rotation_x="0" rotation_y="0" rotation_z="0" size_x="0.1" size_y="10" size_z="2" type="box"/>
			<Geom bouncyness="0.3" color="80003366" friction="0.0" position_x="0" position_y="5" position_z="1" rotation_x="0" rotation_y="0" rotation_z="0" size_x="0.1" size_y="10" size_z="2" type="box"/>
			<!-- gate -->
			<Geom bouncyness="0.3" color="80003366" friction="0.0" position_x="2.20" position_y="5" position_z="0.25" rotation_x="0" rotation_y="0" rotation_z="0" size_x="4.4" size_y="0.1" size_z="0.5" type="box"/>
			<Geom bouncyness="0.3" color="80003366" friction="0.0" position_x="7.80" position_y="5" position_z="0.25" rotation_x="0" rotation_y="0" rotation_z="0" size_x="4.4" size_y="0.1" size_z="0.5" type="box"/>
		</Geoms>
	</Environment>
</World>